hipyschool/__init__.py
hipyschool/locale/hipyschool.pot
hipyschool/locale/en/LC_MESSAGES/pyschool.mo
hipyschool/locale/en/LC_MESSAGES/pyschool.po
hipyschool/locale/es/LC_MESSAGES/pyschool.mo
hipyschool/locale/es/LC_MESSAGES/pyschool.po
hipyschool/print_method/README.rst
hipyschool/print_method/SOLUTION.rst
hipyschool/print_method/__init__.py
hipyschool-1.0.7.dist-info/DESCRIPTION.rst
hipyschool-1.0.7.dist-info/METADATA
hipyschool-1.0.7.dist-info/RECORD
hipyschool-1.0.7.dist-info/WHEEL
hipyschool-1.0.7.dist-info/entry_points.txt
hipyschool-1.0.7.dist-info/metadata.json
hipyschool-1.0.7.dist-info/top_level.txt
