Metadata-Version: 2.0
Name: hipyschool
Version: 1.0.7
Summary: A pyschool story for learning regular expressions.
Home-page: https://github.com/pyschool/hipyschool
Author: Sophilabs
Author-email: hi@sophilabs.co
License: MIT license
Keywords: hipyschool
Platform: UNKNOWN
Classifier: Development Status :: 2 - Pre-Alpha
Classifier: Intended Audience :: Developers
Classifier: License :: OSI Approved :: MIT License
Classifier: Natural Language :: English
Classifier: Programming Language :: Python :: 3
Classifier: Programming Language :: Python :: 3.3
Classifier: Programming Language :: Python :: 3.4
Classifier: Programming Language :: Python :: 3.5
Requires-Dist: story (>=1.2.2)
